{
  "gitSyncId": "684935d02eaef61bf1109ba3_b797d04c-410a-49f6-a8ba-2a988786c7d2",
  "id": "Orders_utils.getOrderTrack",
  "pluginId": "js-plugin",
  "pluginType": "JS",
  "unpublishedAction": {
    "actionConfiguration": {
      "encodeParamsToggle": true,
      "isAsync": true,
      "jsArguments": [],
      "paginationType": "NONE",
      "timeoutInMillisecond": 10000
    },
    "collectionId": "Orders_utils",
    "confirmBeforeExecute": false,
    "datasource": {
      "isAutoGenerated": false,
      "name": "UNUSED_DATASOURCE",
      "pluginId": "js-plugin"
    },
    "dynamicBindingPathList": [
      {
        "key": "body"
      }
    ],
    "executeOnLoad": true,
    "fullyQualifiedName": "utils.getOrderTrack",
    "name": "getOrderTrack",
    "pageId": "Orders",
    "userSetOnLoad": false
  }
}